pymarz/__init__.py
pymarz/client.py
pymarz/utils.py
pymarz/api/__init__.py
pymarz/api/admin.py
pymarz/api/base.py
pymarz/api/config.py
pymarz/api/core.py
pymarz/api/host.py
pymarz/api/inbound.py
pymarz/api/node.py
pymarz/api/subscription.py
pymarz/api/system.py
pymarz/api/template.py
pymarz/api/user.py
pymarz/models/__init__.py
pymarz/models/admin.py
pymarz/models/base.py
pymarz/models/core.py
pymarz/models/message.py
pymarz/models/node.py
pymarz/models/proxy.py
pymarz/models/system.py
pymarz/models/user.py
pymarz/models/user_template.py
pymarz/models/xray_api/__init__.py
pymarz/models/xray_api/account.py
pymarz-1.0.1.dist-info/LICENCE
pymarz-1.0.1.dist-info/METADATA
pymarz-1.0.1.dist-info/WHEEL
pymarz-1.0.1.dist-info/top_level.txt
pymarz-1.0.1.dist-info/RECORD
