Metadata-Version: 2.1
Name: pymarz
Version: 1.0.1
Summary: Asynchronous Python library for interacting with Marzban
Home-page: https://github.com/SSaeedhoseini/pymarz
Author: SSaeedhoseini
Author-email: 
Project-URL: Homepage, https://github.com/SSaeedhoseini/pymarz
Project-URL: Source, https://github.com/SSaeedhoseini/pymarz
Keywords: pymarz,pymarz API,MarzbanAPI,Marzban
Classifier: Programming Language :: Python :: 3
Classifier: License :: OSI Approved :: MIT License
Classifier: Operating System :: OS Independent
Requires-Python: >=3.7
License-File: LICENCE
Requires-Dist: requests
Requires-Dist: asgiref
